{"page":{"name":"Tencent","displayName":"腾讯","description":"腾讯官网","creator":{"editorId":1,"name":"超级管理员","headSculpture":"\\Sonarqube\\1.png","time":"2020-09-22T21:27:54.093469"},"lastUpdater":{"editorId":1,"name":"超级管理员","headSculpture":"\\Sonarqube\\1.png","time":"2020-09-23T15:32:16.8215242"},"discriminator":"StaticPage"},"pageComponents":[{"name":"Text","sign":"1600796823640","parentSign":"1600796380577","pageComponentBaseSetting":{"sortIndex":2,"width":"100%","marginTop":10},"pageLeafSetting":{"pageName":"","pageSize":10,"top":0,"searchKey":""},"pageComponentSettings":{"IEFontSetting":{"name":"IEFontSetting","displayName":"IEFontSetting"},"Setting":{"name":"Setting","displayName":"Setting","textType":"text"}},"os":"Web","pageComponentSigns":[]},{"name":"IEButton","sign":"1600785445605","parentSign":"1600785225933","pageComponentBaseSetting":{"sortIndex":2,"width":""},"pageLeafSetting":{"pageName":"","pageSize":10,"top":0,"searchKey":""},"pageComponentSettings":{"BtnSetting":{"name":"BtnSetting","displayName":"BtnSetting","text":"EN","btnType":"link"},"IECommonStyleSetting":{"name":"IECommonStyleSetting","displayName":"IECommonStyleSetting"}},"os":"Web","pageComponentSigns":[]},{"name":"Container","sign":"1600794901603","parentSign":"1600794631640","pageComponentBaseSetting":{"sortIndex":7,"width":"","position":"absolute","left":"100","top":"100"},"pageLeafSetting":{"pageName":"","pageSize":10,"top":0,"searchKey":""},"pageComponentSettings":{"FlexSetting":{"name":"FlexSetting","displayName":"FlexSetting"},"IECommonStyleSetting":{"name":"IECommonStyleSetting","displayName":"IECommonStyleSetting"}},"os":"Web","pageComponentSigns":["1600794957293"]},{"name":"Text","sign":"1600790447016","parentSign":"1600790338968","pageComponentBaseSetting":{"sortIndex":0,"width":"100%"},"pageLeafSetting":{"pageName":"","pageSize":10,"top":0,"searchKey":""},"pageComponentSettings":{"Setting":{"name":"Setting","displayName":"Setting","textType":"h2","textSource":"#fff"},"IEFontSetting":{"name":"IEFontSetting","displayName":"IEFontSetting"}},"os":"Web","pageComponentSigns":[]},{"name":"Container","sign":"1600793863462","parentSign":"1600793847747","pageComponentBaseSetting":{"sortIndex":0,"width":"1200px"},"pageLeafSetting":{"pageName":"","pageSize":10,"top":0,"searchKey":""},"pageComponentSettings":{"FlexSetting":{"name":"FlexSetting","displayName":"FlexSetting"},"IECommonStyleSetting":{"name":"IECommonStyleSetting","displayName":"IECommonStyleSetting"}},"os":"Web","pageComponentSigns":["1600793913858","1600794084524"]},{"name":"Container","sign":"1600790653365","parentSign":"__Root__","pageComponentBaseSetting":{"sortIndex":3,"width":"100%","marginBottom":90,"backgroundColor":"#1b1f25"},"pageLeafSetting":{"pageName":"","pageSize":10,"top":0,"searchKey":""},"pageComponentSettings":{"FlexSetting":{"name":"FlexSetting","displayName":"FlexSetting","justifyContent":"center"},"IECommonStyleSetting":{"name":"IECommonStyleSetting","displayName":"IECommonStyleSetting"}},"os":"Web","pageComponentSigns":["1600790666804"]},{"name":"Container","sign":"1600791535278","parentSign":"1600790666804","group":"tabs","pageComponentBaseSetting":{"sortIndex":3,"width":"","height":"200px"},"pageLeafSetting":{"pageName":"","pageSize":10,"top":0,"searchKey":""},"pageComponentSettings":{"FlexSetting":{"name":"FlexSetting","displayName":"FlexSetting","justifyContent":"flex-start","alignItems":"center","alignContent":"center"},"IECommonStyleSetting":{"name":"IECommonStyleSetting","displayName":"IECommonStyleSetting"}},"os":"Web","pageComponentSigns":["1600791541311","1600791585644"]},{"name":"Container","sign":"1600790736502","parentSign":"1600790666804","group":"tabs","pageComponentBaseSetting":{"sortIndex":0,"width":"","height":"200px"},"pageLeafSetting":{"pageName":"","pageSize":10,"top":0,"searchKey":""},"pageComponentSettings":{"FlexSetting":{"name":"FlexSetting","displayName":"FlexSetting","alignItems":"center","alignContent":"center"},"IECommonStyleSetting":{"name":"IECommonStyleSetting","displayName":"IECommonStyleSetting"}},"os":"Web","pageComponentSigns":["1600790758597","1600791016461"]},{"name":"Container","sign":"1600791282133","parentSign":"1600790666804","group":"tabs","pageComponentBaseSetting":{"sortIndex":2,"width":"","height":"200px"},"pageLeafSetting":{"pageName":"","pageSize":10,"top":0,"searchKey":""},"pageComponentSettings":{"FlexSetting":{"name":"FlexSetting","displayName":"FlexSetting","alignItems":"center","alignContent":"center"},"IECommonStyleSetting":{"name":"IECommonStyleSetting","displayName":"IECommonStyleSetting"}},"os":"Web","pageComponentSigns":["1600791300954","1600791379578"]},{"name":"RichTextEditor","sign":"1600789574684","parentSign":"1600789518046","pageComponentBaseSetting":{"sortIndex":0,"width":"100%"},"pageLeafSetting":{"pageName":"","pageSize":10,"top":0,"searchKey":""},"pageComponentSettings":{"DefaultSetting":{"name":"DefaultSetting","displayName":"DefaultSetting"}},"os":"Web","pageComponentSigns":[]},{"name":"Container","sign":"1600790891548","parentSign":"1600790666804","group":"contents","pageComponentBaseSetting":{"sortIndex":1,"width":"100%","height":"700px"},"pageLeafSetting":{"pageName":"","pageSize":10,"top":0,"searchKey":""},"pageComponentSettings":{"FlexSetting":{"name":"FlexSetting","displayName":"FlexSetting"}},"os":"Web","pageComponentSigns":["1600791915164","1600791945474","1600791999562","1600792037820"]},{"name":"Container","sign":"1600795350232","parentSign":"1600795342181","pageComponentBaseSetting":{"sortIndex":0,"width":"1200px"},"pageLeafSetting":{"pageName":"","pageSize":10,"top":0,"searchKey":""},"pageComponentSettings":{"FlexSetting":{"name":"FlexSetting","displayName":"FlexSetting"},"IECommonStyleSetting":{"name":"IECommonStyleSetting","displayName":"IECommonStyleSetting"}},"os":"Web","pageComponentSigns":["1600795403953","1600797050589","1600795837151"]},{"name":"Container","sign":"1600781560316","parentSign":"1600781531572","pageComponentBaseSetting":{"sortIndex":0,"width":"1200px","height":"72","className":"zindex"},"pageLeafSetting":{"pageName":"","pageSize":10,"top":0,"searchKey":""},"pageComponentSettings":{"FlexSetting":{"name":"FlexSetting","displayName":"FlexSetting","justifyContent":"space-between","alignItems":"center","alignContent":"center"},"IECommonStyleSetting":{"name":"IECommonStyleSetting","displayName":"IECommonStyleSetting"}},"os":"Web","pageComponentSigns":["1600781625488","1600783476941","1600785225933"]},{"name":"Container","sign":"1600796606440","parentSign":"1600795837151","pageComponentBaseSetting":{"sortIndex":4,"width":"40%","height":"100%"},"pageLeafSetting":{"pageName":"","pageSize":10,"top":0,"searchKey":""},"pageComponentSettings":{"FlexSetting":{"name":"FlexSetting","displayName":"FlexSetting","alignItems":"center","alignContent":"center"},"IECommonStyleSetting":{"name":"IECommonStyleSetting","displayName":"IECommonStyleSetting"}},"os":"Web","pageComponentSigns":["1600796662989"]},{"name":"Container","sign":"1600797372650","parentSign":"__Root__","pageComponentBaseSetting":{"sortIndex":7,"width":"100%","marginTop":35,"marginBottom":20},"pageLeafSetting":{"pageName":"","pageSize":10,"top":0,"searchKey":""},"pageComponentSettings":{"FlexSetting":{"name":"FlexSetting","displayName":"FlexSetting","justifyContent":"center"},"IECommonStyleSetting":{"name":"IECommonStyleSetting","displayName":"IECommonStyleSetting"}},"os":"Web","pageComponentSigns":["1600797387864"]},{"name":"IEAnimation","sign":"1600792497311","parentSign":"1600792429818","pageComponentBaseSetting":{"sortIndex":0,"width":"100%","height":"100%"},"pageLeafSetting":{"pageName":"","pageSize":10,"top":0,"searchKey":""},"pageComponentSettings":{"DefaultSetting":{"name":"DefaultSetting","displayName":"DefaultSetting","time":"hover","direction":"toTop","initValue":20,"isOverHidden":true,"endVal":40}},"os":"Web","pageComponentSigns":["1600792551378","1600792626012"]},{"name":"Text","sign":"1600796819442","parentSign":"1600796380577","pageComponentBaseSetting":{"sortIndex":1,"width":"100%","marginTop":15},"pageLeafSetting":{"pageName":"","pageSize":10,"top":0,"searchKey":""},"pageComponentSettings":{"IEFontSetting":{"name":"IEFontSetting","displayName":"IEFontSetting"},"Setting":{"name":"Setting","displayName":"Setting","textType":"text"}},"os":"Web","pageComponentSigns":[]},{"name":"Text","sign":"1600781625488","parentSign":"1600781560316","pageComponentBaseSetting":{"sortIndex":0,"width":""},"pageLeafSetting":{"pageName":"","pageSize":10,"top":0,"searchKey":""},"pageComponentSettings":{"Setting":{"name":"Setting","displayName":"Setting","textType":"h3","textSource":"#fff"},"IEFontSetting":{"name":"IEFontSetting","displayName":"IEFontSetting","color":"#fff","fontStyle":"italic"}},"os":"Web","pageComponentSigns":[]},{"name":"Container","sign":"1600790071148","parentSign":"1600789825347","pageComponentBaseSetting":{"sortIndex":0,"width":"100%","height":"100%"},"pageLeafSetting":{"pageName":"","pageSize":10,"top":0,"searchKey":""},"pageComponentSettings":{"FlexSetting":{"name":"FlexSetting","displayName":"FlexSetting","alignItems":"center","alignContent":"center"},"IECommonStyleSetting":{"name":"IECommonStyleSetting","displayName":"IECommonStyleSetting"}},"os":"Web","pageComponentSigns":["1600790375754"]},{"name":"IEButton","sign":"1600797729400","parentSign":"1600797591211","pageComponentBaseSetting":{"sortIndex":2,"width":""},"pageLeafSetting":{"pageName":"","pageSize":10,"top":0,"searchKey":""},"pageComponentSettings":{"BtnSetting":{"name":"BtnSetting","displayName":"BtnSetting","text":"网站地图","btnType":"link","size":"middle"},"IECommonStyleSetting":{"name":"IECommonStyleSetting","displayName":"IECommonStyleSetting"}},"os":"Web","pageComponentSigns":[]},{"name":"Container","sign":"1600789518046","parentSign":"__Root__","pageComponentBaseSetting":{"sortIndex":1,"width":"100%","height":"340px"},"pageLeafSetting":{"pageName":"","pageSize":10,"top":0,"searchKey":""},"pageComponentSettings":{"FlexSetting":{"name":"FlexSetting","displayName":"FlexSetting","direction":"column","justifyContent":"center"},"IECommonStyleSetting":{"name":"IECommonStyleSetting","displayName":"IECommonStyleSetting"}},"os":"Web","pageComponentSigns":["1600789574684"]},{"name":"Text","sign":"1600795421155","parentSign":"1600795403953","pageComponentBaseSetting":{"sortIndex":0,"width":""},"pageLeafSetting":{"pageName":"","pageSize":10,"top":0,"searchKey":""},"pageComponentSettings":{"IEFontSetting":{"name":"IEFontSetting","displayName":"IEFontSetting"},"Setting":{"name":"Setting","displayName":"Setting","textType":"h3"}},"os":"Web","pageComponentSigns":[]},{"name":"Text","sign":"1600791016461","parentSign":"1600790736502","pageComponentBaseSetting":{"sortIndex":1,"width":"100%","marginTop":15},"pageLeafSetting":{"pageName":"","pageSize":10,"top":0,"searchKey":""},"pageComponentSettings":{"Setting":{"name":"Setting","displayName":"Setting","textType":"text","textSource":"#fff"},"IEFontSetting":{"name":"IEFontSetting","displayName":"IEFontSetting","fontSize":"16px","color":"#fff"}},"os":"Web","pageComponentSigns":[]},{"name":"Text","sign":"1600791541311","parentSign":"1600791535278","pageComponentBaseSetting":{"sortIndex":0,"width":"100%"},"pageLeafSetting":{"pageName":"","pageSize":10,"top":0,"searchKey":""},"pageComponentSettings":{"IEFontSetting":{"name":"IEFontSetting","displayName":"IEFontSetting","color":"#fff"},"Setting":{"name":"Setting","displayName":"Setting","textType":"h2","textSource":"#fff"}},"os":"Web","pageComponentSigns":[]},{"name":"Text","sign":"1600791379578","parentSign":"1600791282133","pageComponentBaseSetting":{"sortIndex":1,"width":"100%","marginTop":15},"pageLeafSetting":{"pageName":"","pageSize":10,"top":0,"searchKey":""},"pageComponentSettings":{"IEFontSetting":{"name":"IEFontSetting","displayName":"IEFontSetting","fontSize":"16px","color":"#fff"},"Setting":{"name":"Setting","displayName":"Setting","textType":"text","textSource":"#fff"}},"os":"Web","pageComponentSigns":[]},{"name":"Container","sign":"1600794084524","parentSign":"1600793863462","pageComponentBaseSetting":{"sortIndex":1,"width":"50%","height":"100%","padding":"20px"},"pageLeafSetting":{"pageName":"","pageSize":10,"top":0,"searchKey":""},"pageComponentSettings":{"FlexSetting":{"name":"FlexSetting","displayName":"FlexSetting","alignItems":"center","alignContent":"center"},"IECommonStyleSetting":{"name":"IECommonStyleSetting","displayName":"IECommonStyleSetting"}},"os":"Web","pageComponentSigns":["1600794175352"]},{"name":"RichTextEditor","sign":"1600794957293","parentSign":"1600794901603","pageComponentBaseSetting":{"sortIndex":0,"width":"100%","position":"","left":"0","right":"0"},"pageLeafSetting":{"pageName":"","pageSize":10,"top":0,"searchKey":""},"pageComponentSettings":{"DefaultSetting":{"name":"DefaultSetting","displayName":"DefaultSetting"}},"os":"Web","pageComponentSigns":[]},{"name":"Container","sign":"1600792324417","parentSign":"1600790666804","group":"contents","pageComponentBaseSetting":{"sortIndex":5,"width":"100%","height":"700px"},"pageLeafSetting":{"pageName":"","pageSize":10,"top":0,"searchKey":""},"pageComponentSettings":{"FlexSetting":{"name":"FlexSetting","displayName":"FlexSetting","alignItems":"center","alignContent":"center"},"IECommonStyleSetting":{"name":"IECommonStyleSetting","displayName":"IECommonStyleSetting"}},"os":"Web","pageComponentSigns":["1600792333253","1600792382590","1600792429818"]},{"name":"Container","sign":"1600790499081","parentSign":"1600789918386","pageComponentBaseSetting":{"sortIndex":0,"width":"100%","height":"100%"},"pageLeafSetting":{"pageName":"","pageSize":10,"top":0,"searchKey":""},"pageComponentSettings":{"FlexSetting":{"name":"FlexSetting","displayName":"FlexSetting","alignItems":"center","alignContent":"center"},"IECommonStyleSetting":{"name":"IECommonStyleSetting","displayName":"IECommonStyleSetting"}},"os":"Web","pageComponentSigns":["1600790538910"]},{"name":"Container","sign":"1600795403953","parentSign":"1600795350232","pageComponentBaseSetting":{"sortIndex":0,"width":"100%","className":""},"pageLeafSetting":{"pageName":"","pageSize":10,"top":0,"searchKey":""},"pageComponentSettings":{"FlexSetting":{"name":"FlexSetting","displayName":"FlexSetting","alignItems":"center","alignContent":"center"},"IECommonStyleSetting":{"name":"IECommonStyleSetting","displayName":"IECommonStyleSetting"}},"os":"Web","pageComponentSigns":["1600795421155","1600795491619","1600795618462"]},{"name":"IEImg","sign":"1600789918386","parentSign":"1600789782981","pageComponentBaseSetting":{"sortIndex":2,"width":"32%"},"pageLeafSetting":{"pageName":"","pageSize":10,"top":0,"searchKey":""},"pageComponentSettings":{"DefaultSetting":{"name":"DefaultSetting","displayName":"DefaultSetting","position":"onimg"}},"os":"Web","pageComponentSigns":["1600790499081"]},{"name":"IEImg","sign":"1600792382590","parentSign":"1600792324417","pageComponentBaseSetting":{"sortIndex":1,"width":"50%"},"pageLeafSetting":{"pageName":"","pageSize":10,"top":0,"searchKey":""},"pageComponentSettings":{"DefaultSetting":{"name":"DefaultSetting","displayName":"DefaultSetting"}},"os":"Web","pageComponentSigns":[]},{"name":"Container","sign":"1600796380577","parentSign":"1600795837151","pageComponentBaseSetting":{"sortIndex":2,"width":"20%"},"pageLeafSetting":{"pageName":"","pageSize":10,"top":0,"searchKey":""},"pageComponentSettings":{"FlexSetting":{"name":"FlexSetting","displayName":"FlexSetting"},"IECommonStyleSetting":{"name":"IECommonStyleSetting","displayName":"IECommonStyleSetting"}},"os":"Web","pageComponentSigns":["1600796464703","1600796819442","1600796823640","1600796826418","1600796830140"]},{"name":"Text","sign":"1600795884015","parentSign":"1600795868651","pageComponentBaseSetting":{"sortIndex":0,"width":"100%"},"pageLeafSetting":{"pageName":"","pageSize":10,"top":0,"searchKey":""},"pageComponentSettings":{"Setting":{"name":"Setting","displayName":"Setting","textType":"h4"},"IEFontSetting":{"name":"IEFontSetting","displayName":"IEFontSetting"}},"os":"Web","pageComponentSigns":[]},{"name":"Container","sign":"1600796429381","parentSign":"1600795837151","pageComponentBaseSetting":{"sortIndex":3,"width":"20%"},"pageLeafSetting":{"pageName":"","pageSize":10,"top":0,"searchKey":""},"pageComponentSettings":{"FlexSetting":{"name":"FlexSetting","displayName":"FlexSetting"},"IECommonStyleSetting":{"name":"IECommonStyleSetting","displayName":"IECommonStyleSetting"}},"os":"Web","pageComponentSigns":["1600796518324","1600797172610","1600797176540"]},{"name":"Container","sign":"1600781336928","parentSign":"__Root__","pageComponentBaseSetting":{"sortIndex":0,"width":"100%","height":""},"pageLeafSetting":{"pageName":"","pageSize":10,"top":0,"searchKey":""},"pageComponentSettings":{"FlexSetting":{"name":"FlexSetting","displayName":"FlexSetting"},"IECommonStyleSetting":{"name":"IECommonStyleSetting","displayName":"IECommonStyleSetting"}},"os":"Web","pageComponentSigns":["1600781377363","1600781531572"]},{"name":"IEImg","sign":"1600791945474","parentSign":"1600790891548","pageComponentBaseSetting":{"sortIndex":1,"width":"50%"},"pageLeafSetting":{"pageName":"","pageSize":10,"top":0,"searchKey":""},"pageComponentSettings":{"DefaultSetting":{"name":"DefaultSetting","displayName":"DefaultSetting"}},"os":"Web","pageComponentSigns":[]},{"name":"IECarousel","sign":"1600794655781","parentSign":"1600794631640","pageComponentBaseSetting":{"sortIndex":6,"width":"100%"},"pageLeafSetting":{"pageName":"","pageSize":10,"top":0,"searchKey":""},"pageComponentSettings":{"DefaultSetting":{"name":"DefaultSetting","displayName":"DefaultSetting"}},"os":"Web","pageComponentSigns":[1601786865582,"1601786865582_cp_2","1601786865582_cp_3"]},{"name":"IEImg","sign":"1600791915164","parentSign":"1600790891548","pageComponentBaseSetting":{"sortIndex":0,"width":"50%"},"pageLeafSetting":{"pageName":"","pageSize":10,"top":0,"searchKey":""},"pageComponentSettings":{"DefaultSetting":{"name":"DefaultSetting","displayName":"DefaultSetting"}},"os":"Web","pageComponentSigns":[]},{"name":"IEAnimation","sign":"1600787542430","parentSign":"1600787312138","pageComponentBaseSetting":{"sortIndex":1,"width":"","height":"75px","marginLeft":20,"marginRight":20},"pageLeafSetting":{"pageName":"","pageSize":10,"top":0,"searchKey":""},"pageComponentSettings":{"DefaultSetting":{"name":"DefaultSetting","displayName":"DefaultSetting","time":"repeat","direction":"toTop","initValue":100,"isOverHidden":true,"endVal":200}},"os":"Web","pageComponentSigns":["1600787594000","1600788311165"]},{"name":"Container","sign":"1600781531572","parentSign":"1600781336928","pageComponentBaseSetting":{"sortIndex":1,"width":"100%","height":"100vh","position":"absolute"},"pageLeafSetting":{"pageName":"","pageSize":10,"top":0,"searchKey":""},"pageComponentSettings":{"FlexSetting":{"name":"FlexSetting","displayName":"FlexSetting","direction":"column","justifyContent":"center","alignItems":"center","alignContent":"center"},"IECommonStyleSetting":{"name":"IECommonStyleSetting","displayName":"IECommonStyleSetting"}},"os":"Web","pageComponentSigns":["1600781560316","1600787312138"]},{"name":"Container","sign":"1600789741781","parentSign":"__Root__","pageComponentBaseSetting":{"sortIndex":2,"width":"100%","height":"","marginBottom":90},"pageLeafSetting":{"pageName":"","pageSize":10,"top":0,"searchKey":""},"pageComponentSettings":{"FlexSetting":{"name":"FlexSetting","displayName":"FlexSetting","justifyContent":"center"},"IECommonStyleSetting":{"name":"IECommonStyleSetting","displayName":"IECommonStyleSetting"}},"os":"Web","pageComponentSigns":["1600789782981"]},{"name":"Text","sign":"1600790538910","parentSign":"1600790499081","pageComponentBaseSetting":{"sortIndex":0,"width":"100%"},"pageLeafSetting":{"pageName":"","pageSize":10,"top":0,"searchKey":""},"pageComponentSettings":{"Setting":{"name":"Setting","displayName":"Setting","textType":"h2","textSource":"#fff"},"IEFontSetting":{"name":"IEFontSetting","displayName":"IEFontSetting"}},"os":"Web","pageComponentSigns":[]},{"name":"Text","sign":"1600790375754","parentSign":"1600790071148","pageComponentBaseSetting":{"sortIndex":0,"width":"100%"},"pageLeafSetting":{"pageName":"","pageSize":10,"top":0,"searchKey":""},"pageComponentSettings":{"Setting":{"name":"Setting","displayName":"Setting","textType":"h2","textSource":"#fff"},"IEFontSetting":{"name":"IEFontSetting","displayName":"IEFontSetting"}},"os":"Web","pageComponentSigns":[]},{"name":"Container","sign":"1600790338968","parentSign":"1600789900036","pageComponentBaseSetting":{"sortIndex":0,"width":"100%","height":"100%"},"pageLeafSetting":{"pageName":"","pageSize":10,"top":0,"searchKey":""},"pageComponentSettings":{"FlexSetting":{"name":"FlexSetting","displayName":"FlexSetting","alignItems":"center","alignContent":"center"},"IECommonStyleSetting":{"name":"IECommonStyleSetting","displayName":"IECommonStyleSetting"}},"os":"Web","pageComponentSigns":["1600790447016"]},{"name":"IEImg","sign":"1600789900036","parentSign":"1600789782981","pageComponentBaseSetting":{"sortIndex":1,"width":"32%"},"pageLeafSetting":{"pageName":"","pageSize":10,"top":0,"searchKey":""},"pageComponentSettings":{"DefaultSetting":{"name":"DefaultSetting","displayName":"DefaultSetting","position":"onimg"}},"os":"Web","pageComponentSigns":["1600790338968"]},{"name":"IEImg","sign":"1600792037820","parentSign":"1600790891548","pageComponentBaseSetting":{"sortIndex":3,"width":"50%"},"pageLeafSetting":{"pageName":"","pageSize":10,"top":0,"searchKey":""},"pageComponentSettings":{"DefaultSetting":{"name":"DefaultSetting","displayName":"DefaultSetting"}},"os":"Web","pageComponentSigns":[]},{"name":"IEPlaceholder","sign":"1600797050589","parentSign":"1600795350232","pageComponentBaseSetting":{"sortIndex":2,"width":"100%","height":"1px","marginTop":20,"marginBottom":20,"backgroundColor":"#0002"},"pageLeafSetting":{"pageName":"","pageSize":10,"top":0,"searchKey":""},"pageComponentSettings":{},"os":"Web","pageComponentSigns":[]},{"name":"Text","sign":"1600790758597","parentSign":"1600790736502","pageComponentBaseSetting":{"sortIndex":0,"width":"100%"},"pageLeafSetting":{"pageName":"","pageSize":10,"top":0,"searchKey":""},"pageComponentSettings":{"Setting":{"name":"Setting","displayName":"Setting","textType":"h2","textSource":"#fff"},"IEFontSetting":{"name":"IEFontSetting","displayName":"IEFontSetting","color":"#fff"}},"os":"Web","pageComponentSigns":[]},{"name":"IETab","sign":"1600790666804","parentSign":"1600790653365","pageComponentBaseSetting":{"sortIndex":0,"width":"1200px"},"pageLeafSetting":{"pageName":"","pageSize":10,"top":0,"searchKey":""},"pageComponentSettings":{"DefaultSetting":{"name":"DefaultSetting","displayName":"DefaultSetting","tabPosition":"left"}},"os":"Web","pageComponentSigns":["1600790736502","1600790891548","1600791282133","1600791535278","1600792253093","1600792324417"]},{"name":"Text","sign":"1600791300954","parentSign":"1600791282133","pageComponentBaseSetting":{"sortIndex":0,"width":"100%"},"pageLeafSetting":{"pageName":"","pageSize":10,"top":0,"searchKey":""},"pageComponentSettings":{"IEFontSetting":{"name":"IEFontSetting","displayName":"IEFontSetting","fontSize":"","color":"#fff"},"Setting":{"name":"Setting","displayName":"Setting","textType":"h2","textSource":"#fff"}},"os":"Web","pageComponentSigns":[]},{"name":"Text","sign":"1600791585644","parentSign":"1600791535278","pageComponentBaseSetting":{"sortIndex":1,"width":"100%","marginTop":15},"pageLeafSetting":{"pageName":"","pageSize":10,"top":0,"searchKey":""},"pageComponentSettings":{"Setting":{"name":"Setting","displayName":"Setting","textType":"text","textSource":"#fff"},"IEFontSetting":{"name":"IEFontSetting","displayName":"IEFontSetting","fontSize":"16px","color":"#fff"}},"os":"Web","pageComponentSigns":[]},{"name":"IEButton","sign":"1600797612800","parentSign":"1600797591211","pageComponentBaseSetting":{"sortIndex":0,"width":""},"pageLeafSetting":{"pageName":"","pageSize":10,"top":0,"searchKey":""},"pageComponentSettings":{"BtnSetting":{"name":"BtnSetting","displayName":"BtnSetting","text":"法律阳光","btnType":"primary","size":"middle"},"IECommonStyleSetting":{"name":"IECommonStyleSetting","displayName":"IECommonStyleSetting"}},"os":"Web","pageComponentSigns":[]},{"name":"IEVideo","sign":"1600781377363","parentSign":"1600781336928","pageComponentBaseSetting":{"sortIndex":0,"width":"100%","height":"100vh","position":""},"pageLeafSetting":{"pageName":"","pageSize":10,"top":0,"searchKey":""},"pageComponentSettings":{"DefaultSetting":{"name":"DefaultSetting","displayName":"DefaultSetting","autoPlay":true,"loopPlay":true,"hiddenTool":true,"customizeHeight":true},"IEPostFieldSetting":{"name":"IEPostFieldSetting","displayName":"IEPostFieldSetting","postFields":{"id":0,"name":"_","sortIndex":0}}},"os":"Web","pageComponentSigns":[]},{"name":"Container","sign":"1600787312138","parentSign":"1600781531572","pageComponentBaseSetting":{"sortIndex":1,"width":"1200px","height":"","paddingBottom":100,"margin":"auto"},"pageLeafSetting":{"pageName":"","pageSize":10,"top":0,"searchKey":""},"pageComponentSettings":{"FlexSetting":{"name":"FlexSetting","displayName":"FlexSetting","justifyContent":"center","alignItems":"center","alignContent":"center"},"IECommonStyleSetting":{"name":"IECommonStyleSetting","displayName":"IECommonStyleSetting"}},"os":"Web","pageComponentSigns":["1600787464055","1600787542430","1600787674442"]},{"name":"IEImg","sign":"1600789825347","parentSign":"1600789782981","pageComponentBaseSetting":{"sortIndex":0,"width":"32%"},"pageLeafSetting":{"pageName":"","pageSize":10,"top":0,"searchKey":""},"pageComponentSettings":{"DefaultSetting":{"name":"DefaultSetting","displayName":"DefaultSetting","position":"onimg"}},"os":"Web","pageComponentSigns":["1600790071148"]},{"name":"IEButton","sign":"1600785345620","parentSign":"1600785225933","pageComponentBaseSetting":{"sortIndex":1,"width":""},"pageLeafSetting":{"pageName":"","pageSize":10,"top":0,"searchKey":""},"pageComponentSettings":{"BtnSetting":{"name":"BtnSetting","displayName":"BtnSetting","text":"繁","btnType":"link"},"IECommonStyleSetting":{"name":"IECommonStyleSetting","displayName":"IECommonStyleSetting"}},"os":"Web","pageComponentSigns":[]},{"name":"Container","sign":"1600792253093","parentSign":"1600790666804","group":"contents","pageComponentBaseSetting":{"sortIndex":4,"width":"100%","height":"700px"},"pageLeafSetting":{"pageName":"","pageSize":10,"top":0,"searchKey":""},"pageComponentSettings":{"FlexSetting":{"name":"FlexSetting","displayName":"FlexSetting"}},"os":"Web","pageComponentSigns":["1600792268215"]},{"name":"IEImg","sign":"1600792333253","parentSign":"1600792324417","pageComponentBaseSetting":{"sortIndex":0,"width":"50%"},"pageLeafSetting":{"pageName":"","pageSize":10,"top":0,"searchKey":""},"pageComponentSettings":{"DefaultSetting":{"name":"DefaultSetting","displayName":"DefaultSetting"}},"os":"Web","pageComponentSigns":[]},{"name":"IEMenu","sign":"1600783476941","parentSign":"1600781560316","pageComponentBaseSetting":{"sortIndex":1,"width":""},"pageLeafSetting":{"pageName":"","pageSize":10,"top":0,"searchKey":""},"menuName":"Main","pageComponentSettings":{"DefaultSetting":{"name":"DefaultSetting","displayName":"DefaultSetting"},"IEFontSetting":{"name":"IEFontSetting","displayName":"IEFontSetting","fontSize":"16px","color":"#fff","fontWeight":"600"}},"os":"Web","pageComponentSigns":[]},{"name":"RichTextEditor","sign":"1600794175352","parentSign":"1600794084524","pageComponentBaseSetting":{"sortIndex":0,"width":"100%"},"pageLeafSetting":{"pageName":"","pageSize":10,"top":0,"searchKey":""},"pageComponentSettings":{"DefaultSetting":{"name":"DefaultSetting","displayName":"DefaultSetting"}},"os":"Web","pageComponentSigns":[]},{"name":"Container","sign":"1600795342181","parentSign":"__Root__","pageComponentBaseSetting":{"sortIndex":6,"width":"100%"},"pageLeafSetting":{"pageName":"","pageSize":10,"top":0,"searchKey":""},"pageComponentSettings":{"FlexSetting":{"name":"FlexSetting","displayName":"FlexSetting","justifyContent":"center"},"IECommonStyleSetting":{"name":"IECommonStyleSetting","displayName":"IECommonStyleSetting"}},"os":"Web","pageComponentSigns":["1600795350232"]},{"name":"IEButton","sign":"1600795491619","parentSign":"1600795403953","pageComponentBaseSetting":{"sortIndex":1,"width":"","marginLeft":20},"pageLeafSetting":{"pageName":"","pageSize":10,"top":0,"searchKey":""},"pageComponentSettings":{"BtnSetting":{"name":"BtnSetting","displayName":"BtnSetting","btnType":"link","size":"large","icon":"UserOutlined"},"IECommonStyleSetting":{"name":"IECommonStyleSetting","displayName":"IECommonStyleSetting"}},"os":"Web","pageComponentSigns":[]},{"name":"IEButton","sign":"1600795618462","parentSign":"1600795403953","pageComponentBaseSetting":{"sortIndex":2,"width":"","marginLeft":20},"pageLeafSetting":{"pageName":"","pageSize":10,"top":0,"searchKey":""},"pageComponentSettings":{"BtnSetting":{"name":"BtnSetting","displayName":"BtnSetting","btnType":"link","size":"large","icon":"GithubOutlined"},"IECommonStyleSetting":{"name":"IECommonStyleSetting","displayName":"IECommonStyleSetting"}},"os":"Web","pageComponentSigns":[]},{"name":"Container","sign":"1600795868651","parentSign":"1600795837151","pageComponentBaseSetting":{"sortIndex":0,"width":"20%"},"pageLeafSetting":{"pageName":"","pageSize":10,"top":0,"searchKey":""},"pageComponentSettings":{"FlexSetting":{"name":"FlexSetting","displayName":"FlexSetting"},"IECommonStyleSetting":{"name":"IECommonStyleSetting","displayName":"IECommonStyleSetting"}},"os":"Web","pageComponentSigns":["1600795884015","1600795955909","1600796009340","1600796142128"]},{"name":"Text","sign":"1600795955909","parentSign":"1600795868651","pageComponentBaseSetting":{"sortIndex":1,"width":"100%","marginTop":15},"pageLeafSetting":{"pageName":"","pageSize":10,"top":0,"searchKey":""},"pageComponentSettings":{"IEFontSetting":{"name":"IEFontSetting","displayName":"IEFontSetting"},"Setting":{"name":"Setting","displayName":"Setting","textType":"text"}},"os":"Web","pageComponentSigns":[]},{"name":"Text","sign":"1600796009340","parentSign":"1600795868651","pageComponentBaseSetting":{"sortIndex":2,"width":"100%","marginTop":15},"pageLeafSetting":{"pageName":"","pageSize":10,"top":0,"searchKey":""},"pageComponentSettings":{"IEFontSetting":{"name":"IEFontSetting","displayName":"IEFontSetting"},"Setting":{"name":"Setting","displayName":"Setting","textType":"text"}},"os":"Web","pageComponentSigns":[]},{"name":"Container","sign":"1600794631640","parentSign":"__Root__","pageComponentBaseSetting":{"sortIndex":5,"width":"100%","marginBottom":30,"position":"relative"},"pageLeafSetting":{"pageName":"","pageSize":10,"top":0,"searchKey":""},"pageComponentSettings":{"FlexSetting":{"name":"FlexSetting","displayName":"FlexSetting"},"IECommonStyleSetting":{"name":"IECommonStyleSetting","displayName":"IECommonStyleSetting"}},"os":"Web","pageComponentSigns":["1600794655781","1600794901603"]},{"name":"Text","sign":"1600796142128","parentSign":"1600795868651","pageComponentBaseSetting":{"sortIndex":3,"width":"100%","marginTop":15},"pageLeafSetting":{"pageName":"","pageSize":10,"top":0,"searchKey":""},"pageComponentSettings":{"Setting":{"name":"Setting","displayName":"Setting","textType":"text"},"IEFontSetting":{"name":"IEFontSetting","displayName":"IEFontSetting"}},"os":"Web","pageComponentSigns":[]},{"name":"Text","sign":"1600796464703","parentSign":"1600796380577","pageComponentBaseSetting":{"sortIndex":0,"width":"100%"},"pageLeafSetting":{"pageName":"","pageSize":10,"top":0,"searchKey":""},"pageComponentSettings":{"IEFontSetting":{"name":"IEFontSetting","displayName":"IEFontSetting"},"Setting":{"name":"Setting","displayName":"Setting"}},"os":"Web","pageComponentSigns":[]},{"name":"IEImg","sign":"1600792268215","parentSign":"1600792253093","pageComponentBaseSetting":{"sortIndex":0,"width":"100%"},"pageLeafSetting":{"pageName":"","pageSize":10,"top":0,"searchKey":""},"pageComponentSettings":{"DefaultSetting":{"name":"DefaultSetting","displayName":"DefaultSetting"}},"os":"Web","pageComponentSigns":[]},{"name":"Container","sign":"1600797387864","parentSign":"1600797372650","pageComponentBaseSetting":{"sortIndex":0,"width":"1200px"},"pageLeafSetting":{"pageName":"","pageSize":10,"top":0,"searchKey":""},"pageComponentSettings":{"FlexSetting":{"name":"FlexSetting","displayName":"FlexSetting"},"IECommonStyleSetting":{"name":"IECommonStyleSetting","displayName":"IECommonStyleSetting"}},"os":"Web","pageComponentSigns":["1600797591211","1600797482634"]},{"name":"Container","sign":"1600785225933","parentSign":"1600781560316","pageComponentBaseSetting":{"sortIndex":2,"width":""},"pageLeafSetting":{"pageName":"","pageSize":10,"top":0,"searchKey":""},"pageComponentSettings":{"FlexSetting":{"name":"FlexSetting","displayName":"FlexSetting"},"IECommonStyleSetting":{"name":"IECommonStyleSetting","displayName":"IECommonStyleSetting"}},"os":"Web","pageComponentSigns":["1600785281281","1600785345620","1600785445605"]},{"name":"IEButton","sign":"1600785281281","parentSign":"1600785225933","pageComponentBaseSetting":{"sortIndex":0,"width":""},"pageLeafSetting":{"pageName":"","pageSize":10,"top":0,"searchKey":""},"pageComponentSettings":{"BtnSetting":{"name":"BtnSetting","displayName":"BtnSetting","text":"简","btnType":"link"},"IECommonStyleSetting":{"name":"IECommonStyleSetting","displayName":"IECommonStyleSetting"}},"os":"Web","pageComponentSigns":[]},{"name":"IEImg","sign":"1600791999562","parentSign":"1600790891548","pageComponentBaseSetting":{"sortIndex":2,"width":"50%"},"pageLeafSetting":{"pageName":"","pageSize":10,"top":0,"searchKey":""},"pageComponentSettings":{"DefaultSetting":{"name":"DefaultSetting","displayName":"DefaultSetting"}},"os":"Web","pageComponentSigns":[]},{"name":"Text","sign":"1600788311165","parentSign":"1600787542430","pageComponentBaseSetting":{"sortIndex":1,"width":"100%","paddingLeft":20,"paddingRight":20},"pageLeafSetting":{"pageName":"","pageSize":10,"top":0,"searchKey":""},"pageComponentSettings":{"Setting":{"name":"Setting","displayName":"Setting","textType":"text","textSource":"#fff"},"IEFontSetting":{"name":"IEFontSetting","displayName":"IEFontSetting","fontSize":"48px","color":"#fff","fontStyle":"italic"}},"os":"Web","pageComponentSigns":[]},{"name":"Text","sign":"1600787464055","parentSign":"1600787312138","pageComponentBaseSetting":{"sortIndex":0,"width":""},"pageLeafSetting":{"pageName":"","pageSize":10,"top":0,"searchKey":""},"pageComponentSettings":{"Setting":{"name":"Setting","displayName":"Setting","textType":"text","textSource":"#fff"},"IEFontSetting":{"name":"IEFontSetting","displayName":"IEFontSetting","fontSize":"48px","color":"#fff","fontStyle":"italic"}},"os":"Web","pageComponentSigns":[]},{"name":"Text","sign":"1600796518324","parentSign":"1600796429381","pageComponentBaseSetting":{"sortIndex":0,"width":"100%"},"pageLeafSetting":{"pageName":"","pageSize":10,"top":0,"searchKey":""},"pageComponentSettings":{"IEFontSetting":{"name":"IEFontSetting","displayName":"IEFontSetting"},"Setting":{"name":"Setting","displayName":"Setting"}},"os":"Web","pageComponentSigns":[]},{"name":"IEImg","sign":"1600792429818","parentSign":"1600792324417","pageComponentBaseSetting":{"sortIndex":2,"width":"100%"},"pageLeafSetting":{"pageName":"","pageSize":10,"top":0,"searchKey":""},"pageComponentSettings":{"DefaultSetting":{"name":"DefaultSetting","displayName":"DefaultSetting","position":"onimg"}},"os":"Web","pageComponentSigns":["1600792497311"]},{"name":"Text","sign":"1600787594000","parentSign":"1600787542430","pageComponentBaseSetting":{"sortIndex":0,"width":"100%","paddingLeft":20,"paddingRight":20},"pageLeafSetting":{"pageName":"","pageSize":10,"top":0,"searchKey":""},"pageComponentSettings":{"Setting":{"name":"Setting","displayName":"Setting","textType":"text","textSource":"#fff"},"IEFontSetting":{"name":"IEFontSetting","displayName":"IEFontSetting","fontSize":"48px","color":"#fff","fontStyle":"italic"}},"os":"Web","pageComponentSigns":[]},{"name":"Text","sign":"1600796826418","parentSign":"1600796380577","pageComponentBaseSetting":{"sortIndex":3,"width":"100%","marginTop":10},"pageLeafSetting":{"pageName":"","pageSize":10,"top":0,"searchKey":""},"pageComponentSettings":{"Setting":{"name":"Setting","displayName":"Setting","textType":"text"},"IEFontSetting":{"name":"IEFontSetting","displayName":"IEFontSetting"}},"os":"Web","pageComponentSigns":[]},{"name":"Text","sign":"1600796830140","parentSign":"1600796380577","pageComponentBaseSetting":{"sortIndex":4,"width":"100%","marginTop":10},"pageLeafSetting":{"pageName":"","pageSize":10,"top":0,"searchKey":""},"pageComponentSettings":{"Setting":{"name":"Setting","displayName":"Setting","textType":"text"},"IEFontSetting":{"name":"IEFontSetting","displayName":"IEFontSetting"}},"os":"Web","pageComponentSigns":[]},{"name":"Container","sign":"1600795837151","parentSign":"1600795350232","pageComponentBaseSetting":{"sortIndex":3,"width":"100%"},"pageLeafSetting":{"pageName":"","pageSize":10,"top":0,"searchKey":""},"pageComponentSettings":{"FlexSetting":{"name":"FlexSetting","displayName":"FlexSetting"},"IECommonStyleSetting":{"name":"IECommonStyleSetting","displayName":"IECommonStyleSetting"}},"os":"Web","pageComponentSigns":["1600795868651","1600796380577","1600796429381","1600796606440"]},{"name":"Text","sign":"1600797172610","parentSign":"1600796429381","pageComponentBaseSetting":{"sortIndex":1,"width":"100%","marginTop":15},"pageLeafSetting":{"pageName":"","pageSize":10,"top":0,"searchKey":""},"pageComponentSettings":{"Setting":{"name":"Setting","displayName":"Setting","textType":"text"},"IEFontSetting":{"name":"IEFontSetting","displayName":"IEFontSetting"}},"os":"Web","pageComponentSigns":[]},{"name":"Text","sign":"1600797176540","parentSign":"1600796429381","pageComponentBaseSetting":{"sortIndex":2,"width":"100%","marginTop":10},"pageLeafSetting":{"pageName":"","pageSize":10,"top":0,"searchKey":""},"pageComponentSettings":{"Setting":{"name":"Setting","displayName":"Setting","textType":"text"},"IEFontSetting":{"name":"IEFontSetting","displayName":"IEFontSetting"}},"os":"Web","pageComponentSigns":[]},{"name":"IEBottomNav","sign":"1600797482634","parentSign":"1600797387864","pageComponentBaseSetting":{"sortIndex":1,"width":"40%"},"pageLeafSetting":{"pageName":"","pageSize":10,"top":0,"searchKey":""},"pageComponentSettings":{"Setting":{"name":"Setting","displayName":"Setting"}},"os":"Web","pageComponentSigns":[]},{"name":"Container","sign":"1600797591211","parentSign":"1600797387864","pageComponentBaseSetting":{"sortIndex":0,"width":"60%"},"pageLeafSetting":{"pageName":"","pageSize":10,"top":0,"searchKey":""},"pageComponentSettings":{"FlexSetting":{"name":"FlexSetting","displayName":"FlexSetting"},"IECommonStyleSetting":{"name":"IECommonStyleSetting","displayName":"IECommonStyleSetting"}},"os":"Web","pageComponentSigns":["1600797612800","1600797671887","1600797729400"]},{"name":"IEButton","sign":"1600797671887","parentSign":"1600797591211","pageComponentBaseSetting":{"sortIndex":1,"width":""},"pageLeafSetting":{"pageName":"","pageSize":10,"top":0,"searchKey":""},"pageComponentSettings":{"BtnSetting":{"name":"BtnSetting","displayName":"BtnSetting","text":"阳光准则","btnType":"link"},"IECommonStyleSetting":{"name":"IECommonStyleSetting","displayName":"IECommonStyleSetting"}},"os":"Web","pageComponentSigns":[]},{"name":"RichTextEditor","sign":"1600796662989","parentSign":"1600796606440","pageComponentBaseSetting":{"sortIndex":0,"width":"100%"},"pageLeafSetting":{"pageName":"","pageSize":10,"top":0,"searchKey":""},"pageComponentSettings":{"DefaultSetting":{"name":"DefaultSetting","displayName":"DefaultSetting"}},"os":"Web","pageComponentSigns":[]},{"name":"","sign":"__Root__","pageComponentBaseSetting":{"sortIndex":0,"width":"100%"},"pageLeafSetting":{"pageName":"","pageSize":10,"top":0,"searchKey":""},"pageComponentSettings":{},"os":"Web","pageComponentSigns":["1600781336928","1600789518046","1600789741781","1600790653365","1600793847747","1600794631640","1600795342181","1600797372650"]},{"name":"Container","sign":"1600793847747","parentSign":"__Root__","pageComponentBaseSetting":{"sortIndex":4,"width":"100%","height":"","marginBottom":90},"pageLeafSetting":{"pageName":"","pageSize":10,"top":0,"searchKey":""},"pageComponentSettings":{"FlexSetting":{"name":"FlexSetting","displayName":"FlexSetting","justifyContent":"center"},"IECommonStyleSetting":{"name":"IECommonStyleSetting","displayName":"IECommonStyleSetting"}},"os":"Web","pageComponentSigns":["1600793863462"]},{"name":"Container","sign":"1600789782981","parentSign":"1600789741781","pageComponentBaseSetting":{"sortIndex":0,"width":"1200px","height":""},"pageLeafSetting":{"pageName":"","pageSize":10,"top":0,"searchKey":""},"pageComponentSettings":{"FlexSetting":{"name":"FlexSetting","displayName":"FlexSetting","justifyContent":"space-between"},"IECommonStyleSetting":{"name":"IECommonStyleSetting","displayName":"IECommonStyleSetting"}},"os":"Web","pageComponentSigns":["1600789825347","1600789900036","1600789918386"]},{"name":"Text","sign":"1600787674442","parentSign":"1600787312138","pageComponentBaseSetting":{"sortIndex":2,"width":""},"pageLeafSetting":{"pageName":"","pageSize":10,"top":0,"searchKey":""},"pageComponentSettings":{"Setting":{"name":"Setting","displayName":"Setting","textType":"text","textSource":"#fff"},"IEFontSetting":{"name":"IEFontSetting","displayName":"IEFontSetting","fontSize":"48px","color":"#fff","fontStyle":"italic"}},"os":"Web","pageComponentSigns":[]},{"sign":1601786865582,"name":"IEImg","parentSign":"1600794655781","os":"Web","pageComponentBaseSetting":{"sortIndex":0,"width":"100%"},"pageLeafSetting":{"pageName":"","pageSize":10,"top":0,"searchKey":""},"pageComponentSettings":{"DefaultSetting":{"name":"DefaultSetting","displayName":"DefaultSetting"}},"pageComponentSigns":[]},{"sign":"1601786865582_cp_2","name":"IEImg","parentSign":"1600794655781","os":"Web","pageComponentBaseSetting":{"sortIndex":1,"width":"100%"},"pageLeafSetting":{"pageName":"","pageSize":10,"top":0,"searchKey":""},"pageComponentSettings":{"DefaultSetting":{"name":"DefaultSetting","displayName":"DefaultSetting"}},"pageComponentSigns":[]},{"sign":"1601786865582_cp_3","name":"IEImg","parentSign":"1600794655781","os":"Web","pageComponentBaseSetting":{"sortIndex":2,"width":"100%"},"pageLeafSetting":{"pageName":"","pageSize":10,"top":0,"searchKey":""},"pageComponentSettings":{"DefaultSetting":{"name":"DefaultSetting","displayName":"DefaultSetting"}},"pageComponentSigns":[]},{"name":"Text","sign":"1600792551378","parentSign":"1600792497311","pageComponentBaseSetting":{"sortIndex":0,"width":"100%","padding":"10"},"pageLeafSetting":{"pageName":"","pageSize":10,"top":0,"searchKey":""},"pageComponentSettings":{"Setting":{"name":"Setting","displayName":"Setting","textSource":"#fff"},"IEFontSetting":{"name":"IEFontSetting","displayName":"IEFontSetting","color":"#fff"}},"os":"Web","pageComponentSigns":[]},{"name":"Text","sign":"1600792626012","parentSign":"1600792497311","pageComponentBaseSetting":{"sortIndex":1,"width":"100%","padding":"10"},"pageLeafSetting":{"pageName":"","pageSize":10,"top":0,"searchKey":""},"pageComponentSettings":{"Setting":{"name":"Setting","displayName":"Setting","textType":"text","textSource":"#fff"},"IEFontSetting":{"name":"IEFontSetting","displayName":"IEFontSetting","color":"#fff"}},"os":"Web","pageComponentSigns":[]},{"name":"IECarousel","sign":"1600793913858","parentSign":"1600793863462","pageComponentBaseSetting":{"sortIndex":0,"width":"50%","height":"400px"},"pageLeafSetting":{"pageName":"","pageSize":10,"top":0,"searchKey":""},"pageComponentSettings":{"DefaultSetting":{"name":"DefaultSetting","displayName":"DefaultSetting","height":400,"width":350}},"os":"Web","pageComponentSigns":[]},{"name":"","sign":"__Root__","pageComponentBaseSetting":{"sortIndex":0,"width":"100%"},"pageLeafSetting":{"pageName":"","pageSize":10,"top":0,"searchKey":""},"pageComponentSettings":{},"os":"Native","pageComponentSigns":[]}],"defaultComponentDatas":[{"sign":"1600790375754","singleDatas":[{"name":"_","sortIndex":0,"field1":"公司介绍"}]},{"sign":"1600797176540","singleDatas":[{"name":"_","sortIndex":0,"field1":"隐私政策"}]},{"sign":"1600794175352","singleDatas":[{"name":"_","sortIndex":0,"field1":"<p><strong><span style=\"line-height:1\"><span style=\"font-size:28px\">连接</span></span></strong></p><p><strong><span style=\"line-height:1\"><span style=\"font-size:28px\">责任与信任</span></span></strong></p><p><span style=\"font-size:16px\"><span style=\"line-height:2\">聚合微小善行，以科技让世界更美好</span></span></p><p><span style=\"font-size:16px\"><span style=\"line-height:2\">——》</span></span></p>"}]},{"sign":"1600792333253","singleDatas":[{"name":"_","sortIndex":0,"field1":"https://www.tencent.com/data/index/index_link_3_1.jpg"}]},{"sign":"1600793913858","singleDatas":[{"name":"DataList","sortIndex":0,"field1":"腾讯长城保护项目","field2":"腾讯公益慈善基金会与中国文物保护基金会共同合作，吸引公众关注和参与长城保护的文化遗产类公益项目。","field3":"https://www.tencent.com/data/index/index_resp_bg2.jpg"},{"name":"DataList","sortIndex":1,"field1":"腾讯为村","field2":"根据乡村使用场景定制微信公众号，形成由村、乡镇、区县、州市组成的公众号集群服务村民，打造手机上的“为村服务中心”。","field3":"https://www.tencent.com/data/index/index_resp_bg3.jpg"}]},{"sign":"1600792037820","singleDatas":[{"name":"_","sortIndex":0,"field1":"https://www.tencent.com/data/index/index_link_1_4.jpg"}]},{"sign":"1600789574684","singleDatas":[{"name":"_","sortIndex":0,"field1":"<p style=\"text-align:center;\"><span style=\"color:#5f6464\"><span style=\"font-size:24px\"><span style=\"line-height:2\">腾讯是一家以互联网为基础的平台公司，</span></span></span></p><p style=\"text-align:center;\"><span style=\"color:#5f6464\"><span style=\"font-size:24px\"><span style=\"line-height:2\">通过技术丰富互联网用户的生活，助力企业数字化升级。</span></span></span></p><p style=\"text-align:center;\"><span style=\"color:#5f6464\"><span style=\"font-size:24px\"><span style=\"line-height:2\">我们的使命是“用户为本 科技向善”。</span></span></span></p>"}]},{"sign":"1600791585644","singleDatas":[{"name":"_","sortIndex":0,"field1":"探索面向未来的创新科技"}]},{"sign":"1600790447016","singleDatas":[{"name":"_","sortIndex":0,"field1":"企业文化"}]},{"sign":"1600792429818","singleDatas":[{"name":"_","sortIndex":0,"field1":"https://www.tencent.com/data/index/index_link_2_3.jpg"}]},{"sign":"1600789900036","singleDatas":[{"name":"_","sortIndex":0,"field1":"https://www.tencent.com/data/index/index_detail_2.jpg"}]},{"sign":"1600791945474","singleDatas":[{"name":"_","sortIndex":0,"field1":"https://www.tencent.com/data/index/index_link_1_2.jpg"}]},{"sign":"1600781625488","singleDatas":[{"name":"_","sortIndex":0,"field1":"IceEmblem 冰纹"}]},{"sign":"1600792551378","singleDatas":[{"name":"_","sortIndex":0,"field1":"智慧产业"}]},{"sign":"1600792268215","singleDatas":[{"name":"_","sortIndex":0,"field1":"https://www.tencent.com/data/index/index_link_2_1.jpg"}]},{"sign":"1600791541311","singleDatas":[{"name":"_","sortIndex":0,"field1":"连接现在与未来"}]},{"sign":"1600795955909","singleDatas":[{"name":"_","sortIndex":0,"field1":"社会招聘"}]},{"sign":"1600791915164","singleDatas":[{"name":"_","sortIndex":0,"field1":"https://www.tencent.com/data/index/index_link_1_1.jpg"}]},{"sign":"1600792382590","singleDatas":[{"name":"_","sortIndex":0,"field1":"https://www.tencent.com/data/index/index_link_3_2.jpg"}]},{"sign":"1600787464055","singleDatas":[{"name":"_","sortIndex":0,"field1":"连 接"}]},{"sign":"1600790758597","singleDatas":[{"name":"_","sortIndex":0,"field1":"连接用户与时间"}]},{"sign":"1600789825347","singleDatas":[{"name":"_","sortIndex":0,"field1":"https://www.tencent.com/data/index/index_detail_1.jpg"}]},{"sign":"1600789918386","singleDatas":[{"name":"_","sortIndex":0,"field1":"https://www.tencent.com/data/index/index_detail_3.jpg"}]},{"sign":"1600787674442","singleDatas":[{"name":"_","sortIndex":0,"field1":"共 生 未 来"}]},{"sign":"1600796819442","singleDatas":[{"name":"_","sortIndex":0,"field1":"客户服务"}]},{"sign":"1600781377363","singleDatas":[{"name":"_","sortIndex":0,"field1":"https://www.tencent.com/video/index-video.mp4"}]},{"sign":"1600791999562","singleDatas":[{"name":"_","sortIndex":0,"field1":"https://www.tencent.com/data/index/index_link_1_3.jpg"}]},{"sign":"1600787594000","singleDatas":[{"name":"_","sortIndex":0,"field1":"公 益"}]},{"sign":"1600795421155","singleDatas":[{"name":"_","sortIndex":0,"field1":"关注我们"}]},{"sign":"1600796142128","singleDatas":[{"name":"_","sortIndex":0,"field1":"国际招聘"}]},{"sign":"1600795884015","singleDatas":[{"name":"_","sortIndex":0,"field1":"加入我们"}]},{"sign":"1600796830140","singleDatas":[{"name":"_","sortIndex":0,"field1":"媒体及投资者"}]},{"sign":"1600796826418","singleDatas":[{"name":"_","sortIndex":0,"field1":"腾讯采购"}]},{"sign":"1600791300954","singleDatas":[{"name":"_","sortIndex":0,"field1":"连接企业与科技"}]},{"sign":"1600788311165","singleDatas":[{"name":"_","sortIndex":0,"field1":"科 技"}]},{"sign":"1600796518324","singleDatas":[{"name":"_","sortIndex":0,"field1":"法律信息"}]},{"sign":"1600796823640","singleDatas":[{"name":"_","sortIndex":0,"field1":"合作"}]},{"sign":"1600796464703","singleDatas":[{"name":"_","sortIndex":0,"field1":"联系我们"}]},{"sign":"1600792626012","singleDatas":[{"name":"_","sortIndex":0,"field1":"通过云、AI、大数据分析、安全、支付、小程序、LBS等互联网前沿技术和产品，打造智慧产业方案，助力产业数字化升级。"}]},{"sign":"1600796009340","singleDatas":[{"name":"_","sortIndex":0,"field1":"校园招聘"}]},{"sign":"1600791016461","singleDatas":[{"name":"_","sortIndex":0,"field1":"让生活更便捷跟多彩"}]},{"sign":"1600797172610","singleDatas":[{"name":"_","sortIndex":0,"field1":"服务协议"}]},{"sign":"1600790538910","singleDatas":[{"name":"_","sortIndex":0,"field1":"办公地点"}]},{"sign":"1600794957293","singleDatas":[{"name":"_","sortIndex":0,"field1":"<p><strong><span style=\"font-size:24px\">连接</span></strong></p><p><strong><span style=\"font-size:24px\">人才与发展</span></strong></p><p>激发活力，助力成长</p>"}]},{"sign":"1600791379578","singleDatas":[{"name":"_","sortIndex":0,"field1":"数字化助手，助力产业升级"}]},{"sign":"1600796662989","singleDatas":[{"name":"_","sortIndex":0,"field1":"<p style=\"text-align:center;\"><strong><em><span style=\"font-size:32px\"><span style=\"color:#003ba5\">IceEmblem 冰纹</span></span></em></strong></p>"}]},{"id":0,"sign":1601786865582,"singleDatas":[{"id":0,"name":"_","sortIndex":0,"field1":"https://www.tencent.com/data/index/index_develop_bg1.jpg"}]},{"id":0,"sign":"1601786865582_cp_2","singleDatas":[{"id":0,"name":"_","sortIndex":0,"field1":"https://www.tencent.com/data/index/index_develop_bg2.jpg"}]},{"id":0,"sign":"1601786865582_cp_3","singleDatas":[{"id":0,"name":"_","sortIndex":0,"field1":"https://www.tencent.com/data/index/index_develop_bg3.jpg"}]}]}